infer_camembert-0.2.1.dist-info/licenses/LICENSE
infercamembert/__init__.py
infercamembert/__main__.py
infercamembert/_process.py
infercamembert/inference.py
infercamembert/labels.py
infercamembert/parameters.py
infer_camembert-0.2.1.dist-info/METADATA
infer_camembert-0.2.1.dist-info/WHEEL
infer_camembert-0.2.1.dist-info/entry_points.txt
infer_camembert-0.2.1.dist-info/top_level.txt
infer_camembert-0.2.1.dist-info/RECORD
