Metadata-Version: 2.4
Name: infer-camembert
Version: 0.2.1
Summary: Python implementation for text classification inference with CamemBERT fine-tuned models
Author-email: Cyril Dever <cdever@pep-s.com>
License: MIT License
Project-URL: Homepage, https://github.com/cyrildever/infer-camembert
Keywords: ai,transformers,inference,bert,camembert
Classifier: Programming Language :: Python :: 3
Classifier: License :: OSI Approved :: MIT License
Classifier: Operating System :: OS Independent
Requires-Python: >=3.10.2
License-File: LICENSE
Requires-Dist: numpy>=1.25.0
Requires-Dist: torch>=2.1.0
Requires-Dist: transformers>=4.34.1
Dynamic: license-file
